docsuite/__init__.py
docsuite/loader.py
docsuite-0.1.1.dist-info/LICENSE
docsuite-0.1.1.dist-info/METADATA
docsuite-0.1.1.dist-info/WHEEL
docsuite-0.1.1.dist-info/top_level.txt
docsuite-0.1.1.dist-info/RECORD
