Metadata-Version: 2.1
Name: docsuite
Version: 0.1.1
Summary: A unified library to load any document type effortlessly into LangChain for generative AI.
Home-page: https://github.com/Pro-Sifat-Hasan/docsuite
Author: Sifat Hasan
Author-email: sihabhossan633@gmail.com
Classifier: Programming Language :: Python :: 3
Classifier: License :: OSI Approved :: MIT License
Classifier: Operating System :: OS Independent
Requires-Python: >=3.6
License-File: LICENSE
Requires-Dist: langchain-community (>=0.3.7)
Requires-Dist: LangChain (>=0.3.3)
